torchspleeter/__init__.py
torchspleeter/command_interface.py
torchspleeter/estimator.py
torchspleeter/requirements.txt
torchspleeter/unet.py
torchspleeter/checkpoints/2stems/audio_example.mp3
torchspleeter/checkpoints/2stems/testcheckpoint0.ckpt
torchspleeter/checkpoints/2stems/testcheckpoint1.ckpt
torchspleeter/test/test_estimator.py
torchspleeter-0.1.5.dist-info/LICENSE
torchspleeter-0.1.5.dist-info/METADATA
torchspleeter-0.1.5.dist-info/WHEEL
torchspleeter-0.1.5.dist-info/entry_points.txt
torchspleeter-0.1.5.dist-info/top_level.txt
torchspleeter-0.1.5.dist-info/RECORD
