Metadata-Version: 2.1
Name: torchspleeter
Version: 0.1.5
Summary: This provides a port of spleeter in Pytorch
Home-page: https://github.com/sean-bailey
Author: Sean Bailey
Author-email: seanbailey518@gmail.com
Classifier: Programming Language :: Python :: 3
Classifier: License :: OSI Approved :: MIT License
Classifier: Operating System :: OS Independent
Requires-Python: >=3.6
License-File: LICENSE
Requires-Dist: torch
Requires-Dist: numpy
Requires-Dist: librosa
Requires-Dist: pydub
